tri/__init__.py
tri/named_struct/__init__.py
tri.named_struct-0.6.0.dist-info/DESCRIPTION.rst
tri.named_struct-0.6.0.dist-info/METADATA
tri.named_struct-0.6.0.dist-info/RECORD
tri.named_struct-0.6.0.dist-info/WHEEL
tri.named_struct-0.6.0.dist-info/metadata.json
tri.named_struct-0.6.0.dist-info/top_level.txt
