Metadata-Version: 2.0
Name: tri.named-struct
Version: 0.6.0
Summary: tri.named_struct supplies a class that can be used like dictionaries (or via attribute access), but with a predefined set of possible key values
Home-page: UNKNOWN
Author: Johan Lübcke
Author-email: johan.lubcke@trioptima.com
License: BSD
Keywords: tri.named_struct
Platform: UNKNOWN
Classifier: Development Status :: 2 - Pre-Alpha
Classifier: Intended Audience :: Developers
Classifier: License :: OSI Approved :: BSD License
Classifier: Natural Language :: English
Classifier: Programming Language :: Python :: 2
Classifier: Programming Language :: Python :: 2.6
Classifier: Programming Language :: Python :: 2.7
Classifier: Programming Language :: Python :: 3
Classifier: Programming Language :: Python :: 3.3
Requires-Dist: tri.declarative
Requires-Dist: tri.struct
